pyppl_annotate.py
pyppl_annotate-0.0.4.dist-info/entry_points.txt
pyppl_annotate-0.0.4.dist-info/LICENSE
pyppl_annotate-0.0.4.dist-info/WHEEL
pyppl_annotate-0.0.4.dist-info/METADATA
pyppl_annotate-0.0.4.dist-info/RECORD
