Metadata-Version: 2.1
Name: pyppl-annotate
Version: 0.0.4
Summary: Adding long description/annotations for PyPPL processes.
License: MIT
Author: pwwang
Author-email: pwwang@pwwang.com
Requires-Python: >=3.6,<4.0
Classifier: License :: OSI Approved :: MIT License
Classifier: Programming Language :: Python :: 3
Classifier: Programming Language :: Python :: 3.6
Classifier: Programming Language :: Python :: 3.7
Classifier: Programming Language :: Python :: 3.8
Requires-Dist: pyppl (>=3.0.0,<4.0.0)
